{
    "words": [
        {
            "Abated": "कमी"
        },
        {
            "Abandon": "त्याग करणे,सोडून देणे"
        },
        {
            "Abhor": "तिरस्कार करणे"
        },
        {
            "Abiding": "कायमचा,अतूट"
        },
        {
            "Ability": "कौशल्य,ताकद"
        },
        {
            "Abolish": "नष्ट करणे, रद्द करणे"
        },
        {
            "Abortive": "अपयशी,निष्फळ"
        },
        {
            "Abridge": "संक्षिप्त करणे"
        },
        {
            "Abrupt": "अकस्मात"
        },
        {
            "Abscond": "पलायन करणे"
        },
        {
            "Absolutely": "संपूर्णतः,पूर्णपणे"
        },
        {
            "Absolve": "निर्दोष ठरवणे,मुक्त करणे"
        },
        {
            "Abstain from": "दूर राहणे"
        },
        {
            "Abundant": "मुबलक,पुष्कळ"
        },
        {
            "Acknowledge": "मान्य करणे"
        },
        {
            "Accelerate": "गती वाढवणे,वेग देणे"
        },
        {
            "Accord": "एकमताने, सहमतीने"
        },
        {
            "Accumulate": "गोळा करणे,साठवणे"
        },
        {
            "Accurate": "तंतोतंत, काटेकोर"
        },
        {
            "Adamant": "ठाम,अविचल, हटवादी"
        },
        {
            "Abodes": "वसतीस्थान"
        },
        {
            "Adept": "वाकबगार,निपुण"
        },
        {
            "Admonish": "कानपिळ्या देणे"
        },
        {
            "Adeversity": "विप्पती,संकट"
        },
        {
            "Affecting": "हृदयद्रावक"
        },
        {
            "Afflict": "दुखावणे,त्रास देणे"
        },
        {
            "Afraid": "भीतीदायक"
        },
        {
            "Aggravate": "अधिक कठीण करणे"
        },
        {
            "Agile": "चपळ"
        },
        {
            "Alert": "जागृत,सतर्क"
        },
        {
            "Alloy": "धातूंचे मिश्रण"
        },
        {
            "Allure": "आकर्षित,मोहित करणे"
        },
        {
            "Ally": "सहकारी"
        },
        {
            "Ambiguous": "संदिग्ध, अष्पष्ट"
        },
        {
            "Ameliorate": "प्रगती करणे"
        },
        {
            "Amiable": "स्नेहपूर्न"
        },
        {
            "Ample": "विपुल, मुबलक"
        },
        {
            "Alien": "परदेशी,उपरा"
        },
        {
            "Analogy": "समानता, सारखेपणा"
        },
        {
            "Annexation": "अनुबंधन, सामीलीकरण"
        },
        {
            "Antagonism": "शत्रुत्व,विरोध"
        },
        {
            "Antitode": "उतारा, रोगप्रतिकरकशक्ती, प्रतिविष"
        },
        {
            "Attack": "चढाई,हल्ला करणे"
        },
        {
            "Authenticate": "सत्यतेचा दुजोरा"
        },
        {
            "Augurs": "संकेतदर्षक"
        },
        {
            "Audible": "ऐकु येईल असा"
        },
        {
            "Augment": "वाढवणे"
        },
        {
            "Auspicious": "उज्ज्वल भविष्य सूचक"
        },
        {
            "Austere": "साधा आणि काटेकोर"
        },
        {
            "Authentic": "खरा,सत्य"
        },
        {
            "Annihilation": "सर्वनाश"
        },
        {
            "Avaricious": "लोभी,लालची"
        },
        {
            "Aversion": "तीव्र नावड, तिटकारा"
        },
        {
            "Adipose": "लठ्ठ, जाड"
        },
        {
            "Aptitude": "योग्यता, कौशल"
        },
        {
            "Agility": "चपळता"
        },
        {
            "Accolade": "प्रशंसा"
        },
        {
            "Authority": "संमती"
        },
        {
            "Alert": "सावध"
        },
        {
            "Artisan": "कलाकार"
        },
        {
            "Assistance": "सहकार्य"
        },
        {
            "Auxiliary": "सहायक, दुय्यम भूमिका असणारा"
        },
        {
            "Abnegation": "त्याग"
        },
        {
            "Accept": "स्वीकार"
        },
        {
            "Appeal":"आवाहन करणे"
        },
       {
          "Arduous":"कष्टसाध्य"
       } ,

        {
            "Accomplice": ""
        },
        {
            "Accuse": ""
        },
        {
            "Accustomed": ""
        },
        {
            "Acquisition": ""
        },
        {
            "Acquit": ""
        },
        {
            "Active": ""
        },
        {
            "Acumen":""
        },
        {
            "Advance":""
        },
        {
            "Advantage":""
        },
        {
            "Affirm":""
        },
        {
            "Aggresive":""
        },
        {
            "Alleviate":""
        },
        {
            "Absurd":""
        },
        {
            "Agony":""
        },
        {
            "Allow":""
        },
        {
            "Anarchy":""
        },
        {
            "Antipathy":""
        },
        {
            "Appear":""
        },
        {
            "Appreciate":""
        },
        {
            "Arduous":""
        },
        {
            "Arrogant":""
        },
        {
            "Ascending":""
        },
        {
            "Aspiration":""
        },
        {
            "Assent":""
        },
        {
            "Attentive":""
        },
        {
            "Attraction":""
        },
        {
            "Autocracy":""
        },
        {
            "Abbreviate":""
        },
        {
            "Archaic":""
        },
        {
            "Audacious":""
        },
        {
            "Insolvent":""
        },
        {
            "Altruist":""
        },
        {
            "Alternate":""
        },
        {
            "Altercation":""
        },
        {
            "Ambidextrous":""
        },
        {
            "Ambivalent":""
        },
        {
            "Amphibious":""
        },
        {
            "Anthropologist":""
        },
        {
            "Asceticism":""
        },
        {
          "Autobiography":""
        },
        {
            "Autopsy":""
        },
        {
            "Appendectomy":""
        },
        {
            "Anatomy":""
        },
        {
            "Autonomy":""
        },
        {
            "Antisocial":""
        },
        {
            "Antiseptic":""
        },
        {
            "Acute":""
        },
        {
            "Apathy":""
        },
        {
            "Avancular":""
        },
        {
            "Alma-mater":""
        },
        {
            "Agorophobia":""
        },
        {
            "Acrophobia":""
        },
        {
            "Aquaphobia":""
        },
        {
            "Arachnophobia":""
        },
        {
            "Astraphobia":""
        },
        {
            "Atychiphobia":""
        },
        {
            "Aerophobia":""
        },
        {
            "Atheism":""
        },
        {
            "Armistice":""
        },
        {
            "Amazon":""
        },
        {
            "Adroitness":""
        },
        {
            "Astronomer":""
        },
        {
            "Amnesty":""
        },
        {
            "Account for":""
        },
        {
            "Autitorioum":""
        },
        {
            "Auditor":""
        },
        {
            "Apiculture":""
        },
        {
            "Aviary":""
        },
        {
            "Abdicate":""
        },
        {
            "Apostate":""
        },
        {
            "Allegory":""
        },
        {
            "Assimilate":""
        },
        {
            "Adolescene":""
        },
        {
            "Alimony":""
        },
        {
            "Aquatic":""
        },
        {
            "Applause":""
        },
        {
            "Aristocracy":""
        },
        {
            "Alleviate":""
        },
        {
            "Anemia":""
        },
        {
            "Amateur":""
        },
        {
            "Aesthetics":""
        },
        {
            "Aconstics":""
        },
        {
            "Aeronautics":""
        },
        {
            "Audicity":""
        },
        {
            "Aborigines":""
        },
        {
            "Anecdot":""
        },
        {
            "Arsenal":""
        },
        {
            "Arbitrator":""
        },
        {
            "Ambience":""
        },
        {
            "Aphonia":""
        },
        {
            "Amnesia":""
        },
        {
            "Afluent":""
        },
        {
            "Asylum":""
        },
        {
            "Banter": "गप्पाटप्पा"
        },
        {
            "Banished": "निष्कासित"
        },
        {
            "Bankrupt": "दिवाळखोर, कफल्लक"
        },
        {
            "Barbarous": "क्रूर, निर्दयी"
        },
        {
            "Barometer":""
        },
        {
            "Blunder": "चूक"
        },
        {
            "Base": "वाईट,लाचखोर"
        },
        {
            "Beseech": "प्रार्थना"
        },
        {
            "Brash": "उद्धट,दिखाऊ"
        },
        {
            "Brevity": "संक्षेप"
        },
        {
            "Baseless": "बिनबुडाचा"
        },
        {
            "Bashful": "संकोची, लाजाळू"
        },
        {
            "Bare": "उघडा,अनवाणी"
        },
        {
            "Bengin": "निरुपद्रवी"
        },
        {
            "Beside the mark": "मुद्याला सोडून"
        },
        {
            "Bedlam": "पागलखाणा"
        },
        {
            "Benevolence": "दयाभाव, कृपा करणे"
        },
        {
            "Bitter": "कडू"
        },
        {
            "Blithe": "आनंदी, स्वच्छंदी"
        },
        {
            "Bold": "धाडशी"
        },
        {
            "Boisterous": "बडबड्या"
        },
        {
            "Boost": "किंमत, ताकद वाढविणे"
        },
        {
            "Brittle": "नाजुक"
        },
        {
            "Brace": "बळकट करणे"
        },
        {
            "Brave": "शुर,निर्भय"
        },
        {
            "Breed": "पालनपोषण, वाढवणे"
        },
        {
            "Brevity": "संक्षिप्त"
        },
        {
            "Brief": "सूचना, टाचन"
        },
        {
            "Bright": "तेजस्वी,प्रकाशमान"
        },
        {
            "Brisk": "चपळ, उल्हाशी"
        },
        {
            "Brutal": "अमानुष, रानटी"
        },
        {
            "Bucolic": "ग्राम्य, ग्रामीण"
        },
        {
            "Buoyant": "आनंदी, उत्साही"
        },
        {
            "Barren":""
        },
        {
            "Beautiful":""
        },
        {
            "Blessing":""
        },
        {
            "Blunt":""
        },
        {
            "Borrow":""
        },
        {
            "Bravery":""
        },
        {
            "Brawny":""
        },
        {
            "Broad":""
        },
        {
            "Bigot":""
        },
        {
            "Bilingual":""
        },
        {
            "Bigamy":""
        },
        {
            "Binocular":""
        },
        {
            "Biopsy":""
        },
        {
            "Bibliography":""
        },
        {
            "Bibliphile":""
        },
        {
            "Benefactor":""
        },
        {
            "Benevolent":""
        },
        {
            "Bonafied":""
        },
        {
            "Benediction":""
        },
        {
            "Bureaucracy":""
        },
        {
            "Bier":""
        },
        {
            "Bourgeous":""
        },
        {
            "Balled":""
        },
        {
            "Barter":""
        },
        {
            "Bunch":""
        },
        {
            "Blackout":""
        },
        {
            "Cajol": "खुशामत करणे"
        },
        {
            "Calamity": "मोठे संकट,अरिष्ट"
        },
        {
            "Calculated": "निर्धारित, पूर्वनियोजित"
        },
        {
            "Callous": "असंवेदनशील"
        },
        {
            "Candid": "प्रांजळ, मनमोकळा"
        },
        {
            "Capital Offence": "मोठा गुन्हा, मृत्यू दंड योग्य"
        },
        {
            "Carnivore": "मांसाहारी"
        },
        {
            "Catastrophe": "अनर्थ,अरिष्ट"
        },
        {
            "Cautious": "जागरूक,सावध"
        },
        {
            "Cease": "थांबवणे,बंद करणे"
        },
        {
            "Chronic": "गंभीर,भीषण"
        },
        {
            "Coarse": "जाडाभरडा, उद्धट"
        },
        {
            "Crucial": "निर्णायक"
        },
        {
            "Clemency": "दया"
        },
        {
            "Contentment": "समाधान"
        },
        {
            "Catalogue": "सूची,यादी"
        },
        {
            "Celebrated": "ख्यातनाम"
        },
        {
            "Censorship": "परिनिरीक्षण, आक्षेपार्ह भाग वगळणे"
        },
        {
            "Chaos": "गोंधळ"
        },
        {
            "Chastisement": "शिक्षा,शासन"
        },
        {
            "Cheat": "लबाडी, फसवणूक"
        },
        {
            "Chivalry": "मध्ययुगीन सरदारांचे रीतिरिवाज"
        },
        {
            "Circumspect": "दक्ष, सावधान"
        },
        {
            "Civil": "सभ्य"
        },
        {
            "Clandestine": "गुप्त गोष्ट"
        },
        {
            "Coherence": "सुसंगती, सुसूत्रता"
        },
        {
            "Cold": "स्नेहपूर्न नसलेला, भावनाशून्य"
        },
        {
            "Commend": "स्तुती करणे"
        },
        {
            "Commotion": "गोंगाट,कल्लोळ"
        },
        {
            "Companion": "मित्र, सहकारी"
        },
        {
            "Compassionate": "अनुकंपा वाटणारा,दयाळू"
        },
        {
            "Combat": "युद्ध करणे,लढणे"
        },
        {
            "Compel": "बळजबरी करणे,भाग पाडणे"
        },
        {
            "Competence": "क्षमता, सामर्थ्य"
        },
        {
            "Compress": "कोंबने, कमी करणे, संक्षिप्त"
        },
        {
            "Concrete": "निश्चित, स्पष्ट, प्रत्यक्ष"
        },
        {
            "Confidence": "विश्वास, भरोषा"
        },
        {
            "Conjucture": "आणीबाणीची परिस्थिती, निर्णायक क्षण"
        },
        {
            "Conscientious": "विचारी, काळजीपूर्वक"
        },
        {
            "Consensus": "सर्वणुमात, संमती"
        },
        {
            "Considerable": "बराच मोठा, लक्षात येण्यासारखा"
        },
        {
            "Conspicuous": "लक्षवेधी"
        },
        {
            "Constant": "सतत,अखंड"
        },
        {
            "Consumption": "भक्षण"
        },
        {
            "Contempt": "तिरस्कार, घृणा"
        },
        {
            "Contemptible": "घृणास्पद"
        },
        {
            "Contrary": "विरुद्ध, विपरीत"
        },
        {
            "Controversy": "जाहीर मतभेद,वाद"
        },
        {
            "Calamity": "संकट"
        },
        {
            "Convenient": "उत्तम सोयीचा, अनुकूल,योग्य"
        },
        {
            "Conventional": "पारंपरिक"
        },
        {
            "Cordial": "मैत्रीपूर्ण"
        },
        {
            "Collision": "एकामेकावर आदलाने"
        },
        {
            "Collusion": "गुप्त समझोता"
        },
        {
            "Command": "आकर्षित करणे"
        },
        {
            "Confer": "चर्चा करणे"
        },
        {
            "Commend": आकर्षित करणे""
        },
        {
            "Corporal": "शारीरिक"
        },
        {
            "Costly": "महागडा"
        },
        {
            "Courteous": "नम्र,सज्जन"
        },
        {
            "Covert": "लपलेला,गुप्त"
        },
        {
            "Crutial": "गंभीर"
        },
        {
            "Crafty": "लबाड,धूर्त"
        },
        {
            "Credible": "विश्वासार्ह"
        },
        {
            "Credulas": "भोळसर"
        },
        {
            "Creed": "संप्रदाय,पंथ"
        },
        {
            "Crucial": "निर्णायक स्वरूपाचा"
        },
        {
            "Curse": "शिव्याशाप देणे"
        },
        {
            "Cursory": "वरवरचा त्रोटक"
        },
        {
            "Constarint": "बंधन"
        },
        {
            "Consummate": "परिपूर्ण"
        },
        {
            "Cop": "पोलिस"
        },
        {
            "Full complement": "पुर्ण क्षमता"
        },
        {
            "Causal": "च्या शी संबंधित"
        },
        {
            "Cultivate": "मशागत करणे, समृद्ध बनविणे"
        },
        {
            "Counterfeit": "बनावट"
        },
        {
            "Childlike": "पोरकट"
        },
        {
            "Conciet": "आत्मप्रौढी"
        },
        {
            "Callous": "निर्दयी"
        },
        {
            "Competence": "क्षमता"
        },
        {
            "Cite": "कथन करणे"
        },
        {
 "Congenital":"जन्मजात"
        },

        {
            "Casual":"च्या शी संबंधित"
        },
        {
            "Convex":""
        },
        {
            "Care":""
        },
        {
            "Celestial":""
        },
        {
            "Cheerful":""
        },
        {
            "Clean":""
        },
        {
            "Clever":""
        },
        {
            "Cling":""
        },
        {
            "Cognizant":""
        },
        {
            "Coherent":""
        },
        {
            "Collect":""
        },
        {
            "Common":""
        },
        {
            "Compassion":""
        },
        {
            "Conceal":""
        },
        {
            "Concieted":""
        },
        {
            "Concise":""
        },
        {
            "Concord":""
        },
        {
            "Condemn":""
        },
        {
            "Confess":""
        },
        {
            "Congruous":""
        },
        {
            "Conservative":""
        },
        {
            "Cogent":""
        },
        {
            "Cluster":""
        },
        {
            "Crawled":""
        },
        {
            "Contagious":""
        },
        {
            "Contepmt":""
        },
        {
            "Content":""
        },
        {
            "Continue":""
        },
        {
            "Contract":""
        },
        {
            "Converge":""
        },
        {
            "Create":""
        },
        {
            "Creditor":""
        },
        {
            "Crooked":""
        },
        {
            "Crude":""
        },
        {
            "Cruel":""
        },
        {
            "Confirm":""
        },
        {
            "Covetous":""
        },
        {
            "Challenge":""
        },
        {
            "Chiropractor":""
        },
        {
            "Chirographer":""
        },
        {
            "Calligraphy":""
        },
        {
            "Cacography":""
        },
        {
            "Cardiology":""
        },
        {
            "Chronology":""
        },
        {
            "Chronometer":""
        },
        {
            "Circumspection":""
        },
        {
            "Colloqual":""
        },
        {
            "Claustrophobia":""
        },
        {
            "Canine":""
        },
        {
            "Contraband":""
        },
        {
            "Confiscate":""
        },
        {
            "Credulous":""
        },
        {
            "Commuter":""
        },
        {
            "Credentials":""
        },
        {
            "Capitalist":""
        },
        {
            "Contemporary":""
        },
        {
            "Cynic":""
        },
        {
            "Culpable":""
        },
        {
            "Culinary":""
        },
        {
            "Cemetery":""
        },
        {
            "Constellation":""
        },
        {
            "Corpese":""
        },
        {
            "Collaborator":""
        },
        {
            "Colloquial":""
        },
        {
            "Conservation":""
        },
        {
            "Compensate":""
        },
        {
            "Colleagues":""
        },
        {
            "Conscious efforts":""
        },
        {
            "Chauffeur":""
        },
        {
            "Cannibal":""
        },
        {
            "Cagoule":""
        },
        {
            "Centenarian":""
        },
        {
            "Crying evil":""
        },
        {
            "Complaisant":""
        },
        {
            "Charisma":""
        },
        {
            "Consent":""
        },
        {
            "Cynosure":""
        },
        {
            "Charitable":""
        },
        {
            "Congenital": "जन्मजात"
        },
        {
            "Defer":"पुढे ढकलणे"
        },
        {
            "Delightful":"आनंदी"
        },
        {
            "Domitable":"नियंत्रण योग्य"
        },
        {
            "Discount":"सुट"
        },
        {
            "Disparity":"मतभेद"
        },
        {
            "Defend":"प्रतिकार"
        },
        {
            "Deference":"आदर"
        },
        {
            "Dry":"निरुत्साही,सुका"
        },
        {
            "Debility":"क्षिनता,थकवा"
        },
        {
            "Definite":"निश्चित"
        },
        {
            "Dangerous":"धोकादायक"
        },
        {
            "Decision":"निर्णय"
        },
        {
            "Decrease":"कमी,घट"
        },
        {
            "Deep":"सखोल"
        },
        {
            "Defame":"बदनामी"
        },
        {
            "Defence":"बचाव"
        },
        {
            "Delay":"लांबवने"
        },
        {
            "Demon":"असुर"
        },
        {
            "Deplorable":"खेदकारक"
        },
        {
            "Deprive":"हिरवून घेणे"
        },
        {
            "Derogatory":"मानहानीकारक"
        },
        {
            "Destruction":"नष्ट करणे"
        },
        {
            "Detest":"तिटकारा करणे"
        },
        {
            "Detriment":"घातक"
        },
        {
            "Diffuse":"पसरवणे"
        },
        {
            "Disclose":"उघड करणे"
        },
        {
            "Discontent":"असंतोष"
        },
        {
            "Domestic":"घरगुती"
        },
        {
            "Drab":"रटाळ"
        },
        {
            "Duplicity":"फसवणूक"
        },
        {
            "Dwarf":"बुटका"
        },
        {
            "Daggers down": "उघड शत्रुत्व"
        },
        {
            "Debilitating": "कमकुवत,अशक्त"
        },
        {
            "Diamond year": "हीरक महोत्सव"
        },
        {
            "Dainty": "सुंदर आणि नाजूक"
        },
        {
            "Data": "संगणकाने विश्लेषण करायची माहिती"
        },
        {
            "Dazzaling": "नेत्रदीपक"
        },
        {
            "Dearth": "तुटवडा,अभाव"
        },
        {
            "Death": "मृत्यू"
        },
        {
            "Demonstrate": "सिध्द करणे, प्रसिद्ध करणे"
        },
        {
            "Denounce": "दोष देणे"
        },
        {
            "Decay": "ह्रास पावने"
        },
        {
            "Deception": "लबाडी, फसवणूक"
        },
        {
            "Decisive": "निर्णायक स्थिती"
        },
        {
            "Decline": "धुडकावून लावणे"
        },
        {
            "Defame": "बदनामी करणे"
        },
        {
            "Defection": "देशांतर, पक्षांतर"
        },
        {
            "Defend": "संरक्षण,बचाव"
        },
        {
            "Defiant": "उद्धाम, उद्धट"
        },
        {
            "Deficient": "अभावपूर्न, अपूर्ण"
        },
        {
            "Delectable": "संतोषकारक, मन प्रसन्न करणारे"
        },
        {
            "Delicious": "चविष्ट, आवडीचा"
        },
        {
            "Denote": "निर्दोष करणे"
        },
        {
            "Dependence": "पारतंत्र्य, आश्रय"
        },
        {
            "Derision": "उपहास, थट्टा, चेष्टा"
        },
        {
            "Desolate": "निर्जन,ओसाड"
        },
        {
            "Despise": "तिरस्कार करणे"
        },
        {
            "Destitute": "गरीब,बेघर"
        },
        {
            "Destroy": "नष्ट करणे"
        },
        {
            "Deviation": "मार्गच्युती, बहकावा"
        },
        {
            "Devoted": "समर्पित"
        },
        {
            "Didactic": "सुचक, सूचित करणारा"
        },
        {
            "Diligent": "मेहनती,उद्योगी,कष्टाळू"
        },
        {
            "Diminish": "कमी करणे"
        },
        {
            "Diplomatic": "चतुर"
        },
        {
            "Discipline": "शिस्त"
        },
        {
            "Disclaim": "नाकारणे"
        },
        {
            "Discontent": "असंतोष"
        },
        {
            "Disgrace": "बदनामी, लज्जास्पद गोष्ट"
        },
        {
            "Disinterested": "निरपेक्ष, निषपृह"
        },
        {
            "Dismay": "धास्ती,भय,चिंता"
        },
        {
            "Distant": "दूरचा,लांबचा"
        },
        {
            "Diversity": "फरक, विविधता"
        },
        {
            "Divine": "अलौकिक,दैवी,दिव्य"
        },
        {
            "Docile": "शांत, आज्ञाधारक"
        },
        {
            "Domineering": "हुकूमत गाजवणारा"
        },
        {
            "Dreadful": "भयंकर"
        },
        {
            "Dermatology":""
        },
        {
            "Demagogue":""
        },
        {
            "Dipsomania":""
        },
        {
            "Diplomacy":""
        },
        {
            "Democracy":""
        },
        {
            "Dessert":""
        },
        {
            "Delegate":""
        },
        {
            "Dictator":""
        },
        {
            "Dubious":""
        },
        {
            "Detergent":""
        },
        {
            "Draw":""
        },
        {
            "Deism":""
        },
        {
            "Defendant":""
        },
        {
            "Debut":""
        },
        {
            "Dirge":""
        },
        {
            "Despondency":""
        },
        {
            "Demography":""
        },
        {
            "Despite":""
        },
        {
            "Earthly": "एहलोकीचा, ऐहिक"
        },
        {
            "Easily hurt": "हळवा"
        },
        {
            "Ecstasy": "परमानंद, अत्यानंद"
        },
        {
            "Effect": "परिणाम"
        },
        {
            "Enigmatic": "गुढ"
        },
        {
            "Encroach": "अतिक्रमण करणे"
        },
        {
            "Endeavour": "प्रयत्न करणे"
        },
        {
            "Enfeeble": "कमकुवत करणे, खाच्चिकरण"
        },
        {
            "Enlarge": "विस्तार करणे"
        },
        {
            "Entice": "भुलवून नेणे"
        },
        {
            "Enlightened": "प्रबुद्ध, जागृत अवस्था"
        },
        {
            "Erect": "बांधणे, स्थापन करणे,उभारणे"
        },
        {
            "Erratic": "बेभरवशाचा"
        },
        {
            "Erudite": "विद्वान,पंडित"
        },
        {
            "Esteem": "आदर करणे"
        },
        {
            "Estimating": "अंदाज बांधण्यासारखा"
        },
        {
            "Even": "समान, सारखा"
        },
        {
            "Eccentric": "विचित्र, विक्षिप्त"
        },
        {
            "Emphasize": "जोर"
        },
        {
            "Extra-terrestrial bodies": "स्वर्गीय"
        },
        {
            "Exonerated": "निर्दोष"
        },
        {
            "Exceptional": "असाधारण"
        },
        {
            "Excited": "चेतवलेला, उद्धित, क्षुब्ध"
        },
        {
            "Execute": "अमलात आणणे"
        },
        {
            "Exigency": "आणीबाणी"
        },
        {
            "Expand": "प्रसरण पावणे,वाढणे"
        },
        {
            "Expel": "काढून टाकने"
        },
        {
            "Expose": "उघड करून घेणे"
        },
        {
            "Extraordinary": "अलौकिक असाधारण"
        },
        {
            "Extravagant": "खर्चिक, उधळ्या"
        },
        {
            "Extricate": ""
        },
        {
            "Excellent": ""
        },
        {
            "Eager": ""
        },
        {
            "Exorbitant": ""
        },
        {
            "Every eanch": ""
        },
        {
            "Embroynic":""
        },
        {
            "Exodus":""
        },
        {
            "Economy":""
        },
        {
            "Elevate":""
        },
        {
            "Enraged":""
        },
        {
            "Enrich":""
        },
        {
            "Enroll":""
        },
        {
            "Enthrone":""
        },
        {
            "Entry":""
        },
        {
            "Entrance":""
        },
        {
            "Esteemed":""
        },
        {
            "Famous":""
        },
        {
            "Eternal":""
        },
        {
            "Ethical":""
        },
        {
            "Exquisite":""
        },
        {
            "Exotic":""
        },
        {
            "Encourage":""
        },
        {
            "Expansion":""
        },
        {
            "Explicit":""
        },
        {
            "External":""
        },
        {
            "Extraneous":""
        },
        {
            "Exult":""
        },
        {
            "Egoist":""
        },
        {
            "Extrovert":""
        },
        {
            "Entomology":""
        },
        {
            "Empathy":""
        },
        {
            "Exhaustive":""
        },
        {
            "Effeminate":""
        },
        {
            "Etymology":""
        },
        {
            "Emetic":""
        },
        {
            "Epilogue":""
        },
        {
            "Executive":""
        },
        {
            "Elegy":""
        },
        {
            "Epidemic":""
        },
        {
            "Exile":""
        },
        {
            "Epigram":""
        },
        {
            "Extempore":""
        },
        {
            "Equilibrium":""
        },
        {
            "Expiate":""
        },
        {
            "Expecting":""
        },
        {
            "Edible":""
        },
        {
            "Eligible":""
        },
        {
            "Expedition":""
        },
        {
            "Ecology":""
        },
        {
            "Escapist":""
        },
        {
            "Ephoria":""
        },
        {
            "Economical":""
        },
        {
            "Flummoxed": ""
        },
        {
            "Fade": ""
        },
        {
            "El Dorado": ""
        },
        {
            "Fictitious": ""
        },
        {
            "Fantastic": ""
        },
        {
            "Fabricate": ""
        },
        {
            "Fabulous": ""
        },
        {
            "Fanciful": ""
        },
        {
            "Fantastic": ""
        },
        {
            "Fatal": ""
        },
        {
            "Fault": ""
        },
        {
            "Fearful": ""
        },
        {
            "Felicity": ""
        },
        {
            "Ferocious": ""
        },
        {
            "Fictitious": ""
        },
        {
            "Filthy": ""
        },
        {
            "Fleeting": ""
        },
        {
            "Fluctuate": ""
        },
        {
            "Foibles": ""
        },
        {
            "Fortitude": ""
        },
        {
            "Fragile": ""
        },
        {
            "French": ""
        },
        {
            "Frenzy": ""
        },
        {
            "Frugal": ""
        },
        {
            "Fundamental": ""
        },
        {
            "Respect": ""
        },
        {
            "Fickle": ""
        },
        {
            "Forbidden": ""
        },
        {
            "Fair": ""
        },
        {
            "Faithful": ""
        },
        {
            "Fame": ""
        },
        {
            "Fatigue": ""
        },
        {
            "Favour": ""
        },
        {
            "Feminine": ""
        },
        {
            "Fiasco": ""
        },
        {
            "Final": ""
        },
        {
            "Flexible": ""
        },
        {
            "Folly": ""
        },
        {
            "Forgive": ""
        },
        {
            "Foundation": ""
        },
        {
            "Frequent": ""
        },
        {
            "Fresh": ""
        },
        {
            "Friendly": ""
        },
        {
            "Faultless": ""
        },
        {
            "Front": ""
        },
        {
            "Fratricide": ""
        },
        {
            "Fraternity": ""
        },
        {
            "Feline": ""
        },
        {
            "Franchise": ""
        },
        {
            "Feminist": ""
        },
        {
            "Fatalist": ""
        },
        {
            "Flamboyant": ""
        },
        {
            "Fastidious": ""
        },
        {
            "Fanatic": ""
        },
        {
            "Fallow-land": ""
        },
        {
            "Fable": ""
        },
        {
            "Fanaticism": ""
        },
        {
            "Flock": ""
        }
    ]
}
